eryonai/__init__.py
eryonai/model.py
eryonai-0.11.0.dist-info/LICENSE
eryonai-0.11.0.dist-info/METADATA
eryonai-0.11.0.dist-info/WHEEL
eryonai-0.11.0.dist-info/top_level.txt
eryonai-0.11.0.dist-info/RECORD
