Metadata-Version: 2.1
Name: eryonai
Version: 0.11.0
Summary: Eryon AI is an advanced language model designed for interactive tasks.
Author: EryonAI
Author-email: eryon.ai.company@gmail.com
Classifier: Programming Language :: Python :: 3
Classifier: License :: OSI Approved :: MIT License
Classifier: Operating System :: OS Independent
Requires-Python: >=3.6
License-File: LICENSE
Requires-Dist: requests
Requires-Dist: torch
Requires-Dist: transformers
